Workbook

Sheet Instructions
A1: LOAN AMORTIZATION CALCULATOR - USER GUIDE
A3: OVERVIEW
A4: This spreadsheet helps you track multiple loans, calculate payments, and visualize your debt payoff journey.
A6: HOW TO USE
A7: 1. Go to each Credit tab (Credit_1, Credit_2, Credit_3) and enter your loan details in the YELLOW cells.
A8: 2. The spreadsheet will automatically calculate monthly payments, interest, and amortization schedule.
A9: 3. Use the 'Extra Payment' column to simulate additional principal payments and see how much you save.
A10: 4. Mark payments as 'Yes' in the 'Paid' column to track your progress.
A11: 5. The Dashboard tab shows a consolidated view of all your loans automatically.
A12: 6. Adjust the monthly payment amount to see different payoff scenarios.
A14: COLOR LEGEND
A15: YELLOW cells | B15: Editable - Enter your data here
A16: WHITE cells | B16: Calculated automatically - Do not edit
A18: KEY FEATURES
A19: - Supports multiple loans with different interest rates and terms
A20: - Calculates total interest paid over the life of each loan
A21: - Shows the impact of extra payments on total interest and payoff date
A22: - Dashboard provides consolidated view of all debts
A23: - Payment prioritization recommendations based on interest rates
A24: - Monthly cash flow summary by payment date
A26: TIPS FOR PAYING OFF DEBT FASTER
A27: 1. Pay off highest interest rate loans first (Avalanche Method)
A28: 2. Any extra payment goes 100% to principal, reducing future interest
A29: 3. Even small extra payments make a big difference over time
A30: 4. Consider refinancing high-interest loans if possible
... A37: Free to use and share

Sheet Credit_1
A1: LOAN AMORTIZATION SCHEDULE - CREDIT 1
A3: LOAN DETAILS
A4: Loan Name: | B4: Car Loan | D4: Monthly Rate: | E4: =POWER(1+B6,1/12)-1 -> 0.014601687 | G4: Loan Type: | H4: Auto
A5: Principal Amount: | B5: 30000 | D5: Monthly Payment: | E5: =IF(B6>0,PMT(E4,B7,-B5),B5/B7) -> 531.35841 | G5: Monthly Fees/Insurance: | H5: 25
A6: Annual Interest Rate (EA): | B6: 0.19 | D6: Total to Pay: | E6: =E5*B7 -> 63763.009
A7: Loan Term (months): | B7: 120 | D7: Total Interest: | E7: =E6-B5 -> 33763.009
A8: First Payment Date: | B8: 2025-01-15
A10: PROGRESS TRACKING | D10: PROJECTIONS | G10: SAVINGS
A11: Payments Made: | B11: =COUNTIF(J17:J216,"Yes") -> 3 | D11: Estimated Payoff Date: | E11: =EDATE(B8,COUNTIF(B17:B216,">0")-1) -> 48714 | G11: Extra Monthly Payment:
A12: Amount Paid So Far: | B12: =SUMIF(J17:J216,"Yes",H17:H216) -> 3869.0752 | D12: Total Months: | E12: =COUNTIF(B17:B216,">0") -> 101 | G12: Interest Savings: | H12: =E7-C217 -> 8315.0593
A13: Progress: | B13: =IF(COUNTIF(B17:B216,">0")>0,COUNTIF(J17:J216,"Yes")/COUNTIF(B17:B216,">0"),0) -> 0.02970297 | D13: Remaining Balance: | E13: =IF(COUNTIF(J17:J216,"Yes")>0,INDEX(E17:E216,COUNTIF(J17:J216,"Yes")),B5) -> 27498.345
A15: Enter extra payments in the 'Extra Payment' column (yellow) to see how much you can save.
A16: Month | B16: Payment | C16: Interest | D16: Principal | E16: Balance | F16: Fees | G16: Extra Payment | H16: Total Payment | I16: Date | J16: Paid
A17: 1 | B17: =IF($B$5>0,MIN($E$5+G17+$H$11,$B$5+C17),0) -> 1031.3584 | C17: =IF($B$5>0,ROUND($B$5*$E$4,2),0) -> 438.05 | D17: =IF($B$5>0,B17-C17,0) -> 593.30841 | E17: =IF($B$5>0,MAX($B$5-D17,0),0) -> 29406.692 | F17: =IF($B$5>0,$H$5,0) -> 25 | G17: 500 | H17: =IF(B17>0,B17+F17,0) -> 1056.3584 | I17: =$B$8 -> 2025-01-15 | J17: Yes
A18: 2 | B18: =IF(E17>0,MIN($E$5+G18+$H$11,E17+C18),0) -> 731.35841 | C18: =IF(E17>0,ROUND(E17*$E$4,2),0) -> 429.39 | D18: =IF(E17>0,B18-C18,0) -> 301.96841 | E18: =IF(E17>0,MAX(E17-D18,0),0) -> 29104.723 | F18: =IF(E17>0,$H$5,0) -> 25 | G18: 200 | H18: =IF(B18>0,B18+F18,0) -> 756.35841 | I18: =IF(E18>0,EDATE($B$8,A18-1),"") -> 45703 | J18: Yes
A19: 3 | B19: =IF(E18>0,MIN($E$5+G19+$H$11,E18+C19),0) -> 2031.3584 | C19: =IF(E18>0,ROUND(E18*$E$4,2),0) -> 424.98 | D19: =IF(E18>0,B19-C19,0) -> 1606.3784 | E19: =IF(E18>0,MAX(E18-D19,0),0) -> 27498.345 | F19: =IF(E18>0,$H$5,0) -> 25 | G19: 1500 | H19: =IF(B19>0,B19+F19,0) -> 2056.3584 | I19: =IF(E19>0,EDATE($B$8,A19-1),"") -> 45731 | J19: Yes
A20: 4 | B20: =IF(E19>0,MIN($E$5+G20+$H$11,E19+C20),0) -> 531.35841 | C20: =IF(E19>0,ROUND(E19*$E$4,2),0) -> 401.52 | D20: =IF(E19>0,B20-C20,0) -> 129.83841 | E20: =IF(E19>0,MAX(E19-D20,0),0) -> 27368.506 | F20: =IF(E19>0,$H$5,0) -> 25 | G20: 0 | H20: =IF(B20>0,B20+F20,0) -> 556.35841 | I20: =IF(E20>0,EDATE($B$8,A20-1),"") -> 45762 | J20: No
A21: 5 | B21: =IF(E20>0,MIN($E$5+G21+$H$11,E20+C21),0) -> 531.35841 | C21: =IF(E20>0,ROUND(E20*$E$4,2),0) -> 399.63 | D21: =IF(E20>0,B21-C21,0) -> 131.72841 | E21: =IF(E20>0,MAX(E20-D21,0),0) -> 27236.778 | F21: =IF(E20>0,$H$5,0) -> 25 | G21: 0 | H21: =IF(B21>0,B21+F21,0) -> 556.35841 | I21: =IF(E21>0,EDATE($B$8,A21-1),"") -> 45792 | J21: No
A22: 6 | B22: =IF(E21>0,MIN($E$5+G22+$H$11,E21+C22),0) -> 531.35841 | C22: =IF(E21>0,ROUND(E21*$E$4,2),0) -> 397.7 | D22: =IF(E21>0,B22-C22,0) -> 133.65841 | E22: =IF(E21>0,MAX(E21-D22,0),0) -> 27103.12 | F22: =IF(E21>0,$H$5,0) -> 25 | G22: 0 | H22: =IF(B22>0,B22+F22,0) -> 556.35841 | I22: =IF(E22>0,EDATE($B$8,A22-1),"") -> 45823 | J22: No
A23: 7 | B23: =IF(E22>0,MIN($E$5+G23+$H$11,E22+C23),0) -> 531.35841 | C23: =IF(E22>0,ROUND(E22*$E$4,2),0) -> 395.75 | D23: =IF(E22>0,B23-C23,0) -> 135.60841 | E23: =IF(E22>0,MAX(E22-D23,0),0) -> 26967.511 | F23: =IF(E22>0,$H$5,0) -> 25 | G23: 0 | H23: =IF(B23>0,B23+F23,0) -> 556.35841 | I23: =IF(E23>0,EDATE($B$8,A23-1),"") -> 45853 | J23: No
A24: 8 | B24: =IF(E23>0,MIN($E$5+G24+$H$11,E23+C24),0) -> 531.35841 | C24: =IF(E23>0,ROUND(E23*$E$4,2),0) -> 393.77 | D24: =IF(E23>0,B24-C24,0) -> 137.58841 | E24: =IF(E23>0,MAX(E23-D24,0),0) -> 26829.923 | F24: =IF(E23>0,$H$5,0) -> 25 | G24: 0 | H24: =IF(B24>0,B24+F24,0) -> 556.35841 | I24: =IF(E24>0,EDATE($B$8,A24-1),"") -> 45884 | J24: No
A25: 9 | B25: =IF(E24>0,MIN($E$5+G25+$H$11,E24+C25),0) -> 531.35841 | C25: =IF(E24>0,ROUND(E24*$E$4,2),0) -> 391.76 | D25: =IF(E24>0,B25-C25,0) -> 139.59841 | E25: =IF(E24>0,MAX(E24-D25,0),0) -> 26690.324 | F25: =IF(E24>0,$H$5,0) -> 25 | G25: 0 | H25: =IF(B25>0,B25+F25,0) -> 556.35841 | I25: =IF(E25>0,EDATE($B$8,A25-1),"") -> 45915 | J25: No
A26: 10 | B26: =IF(E25>0,MIN($E$5+G26+$H$11,E25+C26),0) -> 531.35841 | C26: =IF(E25>0,ROUND(E25*$E$4,2),0) -> 389.72 | D26: =IF(E25>0,B26-C26,0) -> 141.63841 | E26: =IF(E25>0,MAX(E25-D26,0),0) -> 26548.686 | F26: =IF(E25>0,$H$5,0) -> 25 | G26: 0 | H26: =IF(B26>0,B26+F26,0) -> 556.35841 | I26: =IF(E26>0,EDATE($B$8,A26-1),"") -> 45945 | J26: No
A27: 11 | B27: =IF(E26>0,MIN($E$5+G27+$H$11,E26+C27),0) -> 531.35841 | C27: =IF(E26>0,ROUND(E26*$E$4,2),0) -> 387.66 | D27: =IF(E26>0,B27-C27,0) -> 143.69841 | E27: =IF(E26>0,MAX(E26-D27,0),0) -> 26404.987 | F27: =IF(E26>0,$H$5,0) -> 25 | G27: 0 | H27: =IF(B27>0,B27+F27,0) -> 556.35841 | I27: =IF(E27>0,EDATE($B$8,A27-1),"") -> 45976 | J27: No
A28: 12 | B28: =IF(E27>0,MIN($E$5+G28+$H$11,E27+C28),0) -> 531.35841 | C28: =IF(E27>0,ROUND(E27*$E$4,2),0) -> 385.56 | D28: =IF(E27>0,B28-C28,0) -> 145.79841 | E28: =IF(E27>0,MAX(E27-D28,0),0) -> 26259.189 | F28: =IF(E27>0,$H$5,0) -> 25 | G28: 0 | H28: =IF(B28>0,B28+F28,0) -> 556.35841 | I28: =IF(E28>0,EDATE($B$8,A28-1),"") -> 46006 | J28: No
A29: 13 | B29: =IF(E28>0,MIN($E$5+G29+$H$11,E28+C29),0) -> 531.35841 | C29: =IF(E28>0,ROUND(E28*$E$4,2),0) -> 383.43 | D29: =IF(E28>0,B29-C29,0) -> 147.92841 | E29: =IF(E28>0,MAX(E28-D29,0),0) -> 26111.261 | F29: =IF(E28>0,$H$5,0) -> 25 | G29: 0 | H29: =IF(B29>0,B29+F29,0) -> 556.35841 | I29: =IF(E29>0,EDATE($B$8,A29-1),"") -> 46037 | J29: No
... A216: 200 | B216: =IF(E215>0,MIN($E$5+G216+$H$11,E215+C216),0) -> 0 | C216: =IF(E215>0,ROUND(E215*$E$4,2),0) -> 0 | D216: =IF(E215>0,B216-C216,0) -> 0 | E216: =IF(E215>0,MAX(E215-D216,0),0) -> 0 | F216: =IF(E215>0,$H$5,0) -> 0 | G216: 0 | H216: =IF(B216>0,B216+F216,0) -> 0 | I216: =IF(E216>0,EDATE($B$8,A216-1),"") | J216: No
A217: TOTAL | B217: =SUMIF(B17:B216,">0") -> 55447.95 | C217: =SUMIF(C17:C216,">0") -> 25447.95 | D217: =SUMIF(D17:D216,">0") -> 30000 | F217: =SUMIF(F17:F216,">0") -> 2525 | G217: =SUM(G17:G216) -> 2200 | H217: =SUMIF(H17:H216,">0") -> 57972.95
A219: SUMMARY
A220: Original Principal: | B220: =$B$5 -> 30000
A221: Total Interest Paid: | B221: =C217 -> 25447.95
A222: Total Fees Paid: | B222: =F217 -> 2525
A223: Total Amount Paid: | B223: =H217 -> 57972.95
A224: Total Months: | B224: =COUNTIF(B17:B216,">0") -> 101
A225: Cost Ratio (Total/Principal): | B225: =H217/$B$5 -> 1.9324317
A226: Interest Savings from Extra: | B226: =$E$12 -> 101

Sheet Credit_2
A1: LOAN AMORTIZATION SCHEDULE - CREDIT 2
A3: LOAN DETAILS
A4: Loan Name: | B4: Home Mortgage | D4: Monthly Rate: | E4: =POWER(1+B6,1/12)-1 -> 0.0052616943 | G4: Loan Type: | H4: Mortgage
A5: Principal Amount: | B5: 150000 | D5: Monthly Payment: | E5: =IF(B6>0,PMT(E4,B7,-B5),B5/B7) -> 1291.375 | G5: Monthly Fees/Insurance: | H5: 150
A6: Annual Interest Rate (EA): | B6: 0.065 | D6: Total to Pay: | E6: =E5*B7 -> 232447.5
A7: Loan Term (months): | B7: 180 | D7: Total Interest: | E7: =E6-B5 -> 82447.498
A8: First Payment Date: | B8: 2025-01-01
A10: PROGRESS TRACKING | D10: PROJECTIONS | G10: SAVINGS
A11: Payments Made: | B11: =COUNTIF(J17:J216,"Yes") -> 0 | D11: Estimated Payoff Date: | E11: =EDATE(B8,COUNTIF(B17:B216,">0")-1) -> 51105 | G11: Extra Monthly Payment: | H11: 0
A12: Amount Paid So Far: | B12: =SUMIF(J17:J216,"Yes",H17:H216) -> 0 | D12: Total Months: | E12: =COUNTIF(B17:B216,">0") -> 180 | G12: Interest Savings: | H12: =E7-C217 -> 0.038388628
A13: Progress: | B13: =IF(COUNTIF(B17:B216,">0")>0,COUNTIF(J17:J216,"Yes")/COUNTIF(B17:B216,">0"),0) -> 0 | D13: Remaining Balance: | E13: =IF(COUNTIF(J17:J216,"Yes")>0,INDEX(E17:E216,COUNTIF(J17:J216,"Yes")),B5) -> 150000
A15: Enter extra payments in the 'Extra Payment' column (yellow) to see how much you can save.
A16: Month | B16: Payment | C16: Interest | D16: Principal | E16: Balance | F16: Fees | G16: Extra Payment | H16: Total Payment | I16: Date | J16: Paid
A17: 1 | B17: =IF($B$5>0,MIN($E$5+G17+$H$11,$B$5+C17),0) -> 1291.375 | C17: =IF($B$5>0,ROUND($B$5*$E$4,2),0) -> 789.25 | D17: =IF($B$5>0,B17-C17,0) -> 502.12499 | E17: =IF($B$5>0,MAX($B$5-D17,0),0) -> 149497.88 | F17: =IF($B$5>0,$H$5,0) -> 150 | G17: 0 | H17: =IF(B17>0,B17+F17,0) -> 1441.375 | I17: =$B$8 -> 2025-01-01 | J17: No
A18: 2 | B18: =IF(E17>0,MIN($E$5+G18+$H$11,E17+C18),0) -> 1291.375 | C18: =IF(E17>0,ROUND(E17*$E$4,2),0) -> 786.61 | D18: =IF(E17>0,B18-C18,0) -> 504.76499 | E18: =IF(E17>0,MAX(E17-D18,0),0) -> 148993.11 | F18: =IF(E17>0,$H$5,0) -> 150 | G18: 0 | H18: =IF(B18>0,B18+F18,0) -> 1441.375 | I18: =IF(E18>0,EDATE($B$8,A18-1),"") -> 45689 | J18: No
A19: 3 | B19: =IF(E18>0,MIN($E$5+G19+$H$11,E18+C19),0) -> 1291.375 | C19: =IF(E18>0,ROUND(E18*$E$4,2),0) -> 783.96 | D19: =IF(E18>0,B19-C19,0) -> 507.41499 | E19: =IF(E18>0,MAX(E18-D19,0),0) -> 148485.7 | F19: =IF(E18>0,$H$5,0) -> 150 | G19: 0 | H19: =IF(B19>0,B19+F19,0) -> 1441.375 | I19: =IF(E19>0,EDATE($B$8,A19-1),"") -> 45717 | J19: No
A20: 4 | B20: =IF(E19>0,MIN($E$5+G20+$H$11,E19+C20),0) -> 1291.375 | C20: =IF(E19>0,ROUND(E19*$E$4,2),0) -> 781.29 | D20: =IF(E19>0,B20-C20,0) -> 510.08499 | E20: =IF(E19>0,MAX(E19-D20,0),0) -> 147975.61 | F20: =IF(E19>0,$H$5,0) -> 150 | G20: 0 | H20: =IF(B20>0,B20+F20,0) -> 1441.375 | I20: =IF(E20>0,EDATE($B$8,A20-1),"") -> 45748 | J20: No
A21: 5 | B21: =IF(E20>0,MIN($E$5+G21+$H$11,E20+C21),0) -> 1291.375 | C21: =IF(E20>0,ROUND(E20*$E$4,2),0) -> 778.6 | D21: =IF(E20>0,B21-C21,0) -> 512.77499 | E21: =IF(E20>0,MAX(E20-D21,0),0) -> 147462.84 | F21: =IF(E20>0,$H$5,0) -> 150 | G21: 0 | H21: =IF(B21>0,B21+F21,0) -> 1441.375 | I21: =IF(E21>0,EDATE($B$8,A21-1),"") -> 45778 | J21: No
A22: 6 | B22: =IF(E21>0,MIN($E$5+G22+$H$11,E21+C22),0) -> 1291.375 | C22: =IF(E21>0,ROUND(E21*$E$4,2),0) -> 775.9 | D22: =IF(E21>0,B22-C22,0) -> 515.47499 | E22: =IF(E21>0,MAX(E21-D22,0),0) -> 146947.36 | F22: =IF(E21>0,$H$5,0) -> 150 | G22: 0 | H22: =IF(B22>0,B22+F22,0) -> 1441.375 | I22: =IF(E22>0,EDATE($B$8,A22-1),"") -> 45809 | J22: No
A23: 7 | B23: =IF(E22>0,MIN($E$5+G23+$H$11,E22+C23),0) -> 1291.375 | C23: =IF(E22>0,ROUND(E22*$E$4,2),0) -> 773.19 | D23: =IF(E22>0,B23-C23,0) -> 518.18499 | E23: =IF(E22>0,MAX(E22-D23,0),0) -> 146429.18 | F23: =IF(E22>0,$H$5,0) -> 150 | G23: 0 | H23: =IF(B23>0,B23+F23,0) -> 1441.375 | I23: =IF(E23>0,EDATE($B$8,A23-1),"") -> 45839 | J23: No
A24: 8 | B24: =IF(E23>0,MIN($E$5+G24+$H$11,E23+C24),0) -> 1291.375 | C24: =IF(E23>0,ROUND(E23*$E$4,2),0) -> 770.47 | D24: =IF(E23>0,B24-C24,0) -> 520.90499 | E24: =IF(E23>0,MAX(E23-D24,0),0) -> 145908.27 | F24: =IF(E23>0,$H$5,0) -> 150 | G24: 0 | H24: =IF(B24>0,B24+F24,0) -> 1441.375 | I24: =IF(E24>0,EDATE($B$8,A24-1),"") -> 45870 | J24: No
A25: 9 | B25: =IF(E24>0,MIN($E$5+G25+$H$11,E24+C25),0) -> 1291.375 | C25: =IF(E24>0,ROUND(E24*$E$4,2),0) -> 767.72 | D25: =IF(E24>0,B25-C25,0) -> 523.65499 | E25: =IF(E24>0,MAX(E24-D25,0),0) -> 145384.62 | F25: =IF(E24>0,$H$5,0) -> 150 | G25: 0 | H25: =IF(B25>0,B25+F25,0) -> 1441.375 | I25: =IF(E25>0,EDATE($B$8,A25-1),"") -> 45901 | J25: No
A26: 10 | B26: =IF(E25>0,MIN($E$5+G26+$H$11,E25+C26),0) -> 1291.375 | C26: =IF(E25>0,ROUND(E25*$E$4,2),0) -> 764.97 | D26: =IF(E25>0,B26-C26,0) -> 526.40499 | E26: =IF(E25>0,MAX(E25-D26,0),0) -> 144858.21 | F26: =IF(E25>0,$H$5,0) -> 150 | G26: 0 | H26: =IF(B26>0,B26+F26,0) -> 1441.375 | I26: =IF(E26>0,EDATE($B$8,A26-1),"") -> 45931 | J26: No
A27: 11 | B27: =IF(E26>0,MIN($E$5+G27+$H$11,E26+C27),0) -> 1291.375 | C27: =IF(E26>0,ROUND(E26*$E$4,2),0) -> 762.2 | D27: =IF(E26>0,B27-C27,0) -> 529.17499 | E27: =IF(E26>0,MAX(E26-D27,0),0) -> 144329.04 | F27: =IF(E26>0,$H$5,0) -> 150 | G27: 0 | H27: =IF(B27>0,B27+F27,0) -> 1441.375 | I27: =IF(E27>0,EDATE($B$8,A27-1),"") -> 45962 | J27: No
A28: 12 | B28: =IF(E27>0,MIN($E$5+G28+$H$11,E27+C28),0) -> 1291.375 | C28: =IF(E27>0,ROUND(E27*$E$4,2),0) -> 759.42 | D28: =IF(E27>0,B28-C28,0) -> 531.95499 | E28: =IF(E27>0,MAX(E27-D28,0),0) -> 143797.08 | F28: =IF(E27>0,$H$5,0) -> 150 | G28: 0 | H28: =IF(B28>0,B28+F28,0) -> 1441.375 | I28: =IF(E28>0,EDATE($B$8,A28-1),"") -> 45992 | J28: No
A29: 13 | B29: =IF(E28>0,MIN($E$5+G29+$H$11,E28+C29),0) -> 1291.375 | C29: =IF(E28>0,ROUND(E28*$E$4,2),0) -> 756.62 | D29: =IF(E28>0,B29-C29,0) -> 534.75499 | E29: =IF(E28>0,MAX(E28-D29,0),0) -> 143262.33 | F29: =IF(E28>0,$H$5,0) -> 150 | G29: 0 | H29: =IF(B29>0,B29+F29,0) -> 1441.375 | I29: =IF(E29>0,EDATE($B$8,A29-1),"") -> 46023 | J29: No
... A216: 200 | B216: =IF(E215>0,MIN($E$5+G216+$H$11,E215+C216),0) -> 0 | C216: =IF(E215>0,ROUND(E215*$E$4,2),0) -> 0 | D216: =IF(E215>0,B216-C216,0) -> 0 | E216: =IF(E215>0,MAX(E215-D216,0),0) -> 0 | F216: =IF(E215>0,$H$5,0) -> 0 | G216: 0 | H216: =IF(B216>0,B216+F216,0) -> 0 | I216: =IF(E216>0,EDATE($B$8,A216-1),"") | J216: No
A217: TOTAL | B217: =SUMIF(B17:B216,">0") -> 232447.46 | C217: =SUMIF(C17:C216,">0") -> 82447.46 | D217: =SUMIF(D17:D216,">0") -> 150000 | F217: =SUMIF(F17:F216,">0") -> 27000 | G217: =SUM(G17:G216) -> 0 | H217: =SUMIF(H17:H216,">0") -> 259447.46
A219: SUMMARY
A220: Original Principal: | B220: =$B$5 -> 150000
A221: Total Interest Paid: | B221: =C217 -> 82447.46
A222: Total Fees Paid: | B222: =F217 -> 27000
A223: Total Amount Paid: | B223: =H217 -> 259447.46
A224: Total Months: | B224: =COUNTIF(B17:B216,">0") -> 180
A225: Cost Ratio (Total/Principal): | B225: =H217/$B$5 -> 1.7296497
A226: Interest Savings from Extra: | B226: =$E$12 -> 180

Sheet Credit_3
A1: LOAN AMORTIZATION SCHEDULE - CREDIT 3
A3: LOAN DETAILS
A4: Loan Name: | B4: Personal Loan | D4: Monthly Rate: | E4: =POWER(1+B6,1/12)-1 -> 0.011714917 | G4: Loan Type: | H4: Personal
A5: Principal Amount: | B5: 10000 | D5: Monthly Payment: | E5: =IF(B6>0,PMT(E4,B7,-B5),B5/B7) -> 342.05758 | G5: Monthly Fees/Insurance: | H5: 15
A6: Annual Interest Rate (EA): | B6: 0.15 | D6: Total to Pay: | E6: =E5*B7 -> 12314.073
A7: Loan Term (months): | B7: 36 | D7: Total Interest: | E7: =E6-B5 -> 2314.0729
A8: First Payment Date: | B8: 2025-02-01
A10: PROGRESS TRACKING | D10: PROJECTIONS | G10: SAVINGS
A11: Payments Made: | B11: =COUNTIF(J17:J216,"Yes") -> 0 | D11: Estimated Payoff Date: | E11: =EDATE(B8,COUNTIF(B17:B216,">0")-1) -> 46753 | G11: Extra Monthly Payment: | H11: 0
A12: Amount Paid So Far: | B12: =SUMIF(J17:J216,"Yes",H17:H216) -> 0 | D12: Total Months: | E12: =COUNTIF(B17:B216,">0") -> 36 | G12: Interest Savings: | H12: =E7-C217 -> 0.0029299227
A13: Progress: | B13: =IF(COUNTIF(B17:B216,">0")>0,COUNTIF(J17:J216,"Yes")/COUNTIF(B17:B216,">0"),0) -> 0 | D13: Remaining Balance: | E13: =IF(COUNTIF(J17:J216,"Yes")>0,INDEX(E17:E216,COUNTIF(J17:J216,"Yes")),B5) -> 10000
A15: Enter extra payments in the 'Extra Payment' column (yellow) to see how much you can save.
A16: Month | B16: Payment | C16: Interest | D16: Principal | E16: Balance | F16: Fees | G16: Extra Payment | H16: Total Payment | I16: Date | J16: Paid
A17: 1 | B17: =IF($B$5>0,MIN($E$5+G17+$H$11,$B$5+C17),0) -> 342.05758 | C17: =IF($B$5>0,ROUND($B$5*$E$4,2),0) -> 117.15 | D17: =IF($B$5>0,B17-C17,0) -> 224.90758 | E17: =IF($B$5>0,MAX($B$5-D17,0),0) -> 9775.0924 | F17: =IF($B$5>0,$H$5,0) -> 15 | G17: 0 | H17: =IF(B17>0,B17+F17,0) -> 357.05758 | I17: =$B$8 -> 2025-02-01 | J17: No
A18: 2 | B18: =IF(E17>0,MIN($E$5+G18+$H$11,E17+C18),0) -> 342.05758 | C18: =IF(E17>0,ROUND(E17*$E$4,2),0) -> 114.51 | D18: =IF(E17>0,B18-C18,0) -> 227.54758 | E18: =IF(E17>0,MAX(E17-D18,0),0) -> 9547.5448 | F18: =IF(E17>0,$H$5,0) -> 15 | G18: 0 | H18: =IF(B18>0,B18+F18,0) -> 357.05758 | I18: =IF(E18>0,EDATE($B$8,A18-1),"") -> 45717 | J18: No
A19: 3 | B19: =IF(E18>0,MIN($E$5+G19+$H$11,E18+C19),0) -> 342.05758 | C19: =IF(E18>0,ROUND(E18*$E$4,2),0) -> 111.85 | D19: =IF(E18>0,B19-C19,0) -> 230.20758 | E19: =IF(E18>0,MAX(E18-D19,0),0) -> 9317.3373 | F19: =IF(E18>0,$H$5,0) -> 15 | G19: 0 | H19: =IF(B19>0,B19+F19,0) -> 357.05758 | I19: =IF(E19>0,EDATE($B$8,A19-1),"") -> 45748 | J19: No
A20: 4 | B20: =IF(E19>0,MIN($E$5+G20+$H$11,E19+C20),0) -> 342.05758 | C20: =IF(E19>0,ROUND(E19*$E$4,2),0) -> 109.15 | D20: =IF(E19>0,B20-C20,0) -> 232.90758 | E20: =IF(E19>0,MAX(E19-D20,0),0) -> 9084.4297 | F20: =IF(E19>0,$H$5,0) -> 15 | G20: 0 | H20: =IF(B20>0,B20+F20,0) -> 357.05758 | I20: =IF(E20>0,EDATE($B$8,A20-1),"") -> 45778 | J20: No
A21: 5 | B21: =IF(E20>0,MIN($E$5+G21+$H$11,E20+C21),0) -> 342.05758 | C21: =IF(E20>0,ROUND(E20*$E$4,2),0) -> 106.42 | D21: =IF(E20>0,B21-C21,0) -> 235.63758 | E21: =IF(E20>0,MAX(E20-D21,0),0) -> 8848.7921 | F21: =IF(E20>0,$H$5,0) -> 15 | G21: 0 | H21: =IF(B21>0,B21+F21,0) -> 357.05758 | I21: =IF(E21>0,EDATE($B$8,A21-1),"") -> 45809 | J21: No
A22: 6 | B22: =IF(E21>0,MIN($E$5+G22+$H$11,E21+C22),0) -> 342.05758 | C22: =IF(E21>0,ROUND(E21*$E$4,2),0) -> 103.66 | D22: =IF(E21>0,B22-C22,0) -> 238.39758 | E22: =IF(E21>0,MAX(E21-D22,0),0) -> 8610.3945 | F22: =IF(E21>0,$H$5,0) -> 15 | G22: 0 | H22: =IF(B22>0,B22+F22,0) -> 357.05758 | I22: =IF(E22>0,EDATE($B$8,A22-1),"") -> 45839 | J22: No
A23: 7 | B23: =IF(E22>0,MIN($E$5+G23+$H$11,E22+C23),0) -> 342.05758 | C23: =IF(E22>0,ROUND(E22*$E$4,2),0) -> 100.87 | D23: =IF(E22>0,B23-C23,0) -> 241.18758 | E23: =IF(E22>0,MAX(E22-D23,0),0) -> 8369.2069 | F23: =IF(E22>0,$H$5,0) -> 15 | G23: 0 | H23: =IF(B23>0,B23+F23,0) -> 357.05758 | I23: =IF(E23>0,EDATE($B$8,A23-1),"") -> 45870 | J23: No
A24: 8 | B24: =IF(E23>0,MIN($E$5+G24+$H$11,E23+C24),0) -> 342.05758 | C24: =IF(E23>0,ROUND(E23*$E$4,2),0) -> 98.04 | D24: =IF(E23>0,B24-C24,0) -> 244.01758 | E24: =IF(E23>0,MAX(E23-D24,0),0) -> 8125.1893 | F24: =IF(E23>0,$H$5,0) -> 15 | G24: 0 | H24: =IF(B24>0,B24+F24,0) -> 357.05758 | I24: =IF(E24>0,EDATE($B$8,A24-1),"") -> 45901 | J24: No
A25: 9 | B25: =IF(E24>0,MIN($E$5+G25+$H$11,E24+C25),0) -> 342.05758 | C25: =IF(E24>0,ROUND(E24*$E$4,2),0) -> 95.19 | D25: =IF(E24>0,B25-C25,0) -> 246.86758 | E25: =IF(E24>0,MAX(E24-D25,0),0) -> 7878.3218 | F25: =IF(E24>0,$H$5,0) -> 15 | G25: 0 | H25: =IF(B25>0,B25+F25,0) -> 357.05758 | I25: =IF(E25>0,EDATE($B$8,A25-1),"") -> 45931 | J25: No
A26: 10 | B26: =IF(E25>0,MIN($E$5+G26+$H$11,E25+C26),0) -> 342.05758 | C26: =IF(E25>0,ROUND(E25*$E$4,2),0) -> 92.29 | D26: =IF(E25>0,B26-C26,0) -> 249.76758 | E26: =IF(E25>0,MAX(E25-D26,0),0) -> 7628.5542 | F26: =IF(E25>0,$H$5,0) -> 15 | G26: 0 | H26: =IF(B26>0,B26+F26,0) -> 357.05758 | I26: =IF(E26>0,EDATE($B$8,A26-1),"") -> 45962 | J26: No
A27: 11 | B27: =IF(E26>0,MIN($E$5+G27+$H$11,E26+C27),0) -> 342.05758 | C27: =IF(E26>0,ROUND(E26*$E$4,2),0) -> 89.37 | D27: =IF(E26>0,B27-C27,0) -> 252.68758 | E27: =IF(E26>0,MAX(E26-D27,0),0) -> 7375.8666 | F27: =IF(E26>0,$H$5,0) -> 15 | G27: 0 | H27: =IF(B27>0,B27+F27,0) -> 357.05758 | I27: =IF(E27>0,EDATE($B$8,A27-1),"") -> 45992 | J27: No
A28: 12 | B28: =IF(E27>0,MIN($E$5+G28+$H$11,E27+C28),0) -> 342.05758 | C28: =IF(E27>0,ROUND(E27*$E$4,2),0) -> 86.41 | D28: =IF(E27>0,B28-C28,0) -> 255.64758 | E28: =IF(E27>0,MAX(E27-D28,0),0) -> 7120.219 | F28: =IF(E27>0,$H$5,0) -> 15 | G28: 0 | H28: =IF(B28>0,B28+F28,0) -> 357.05758 | I28: =IF(E28>0,EDATE($B$8,A28-1),"") -> 46023 | J28: No
A29: 13 | B29: =IF(E28>0,MIN($E$5+G29+$H$11,E28+C29),0) -> 342.05758 | C29: =IF(E28>0,ROUND(E28*$E$4,2),0) -> 83.41 | D29: =IF(E28>0,B29-C29,0) -> 258.64758 | E29: =IF(E28>0,MAX(E28-D29,0),0) -> 6861.5714 | F29: =IF(E28>0,$H$5,0) -> 15 | G29: 0 | H29: =IF(B29>0,B29+F29,0) -> 357.05758 | I29: =IF(E29>0,EDATE($B$8,A29-1),"") -> 46054 | J29: No
... A216: 200 | B216: =IF(E215>0,MIN($E$5+G216+$H$11,E215+C216),0) -> 0 | C216: =IF(E215>0,ROUND(E215*$E$4,2),0) -> 0 | D216: =IF(E215>0,B216-C216,0) -> 0 | E216: =IF(E215>0,MAX(E215-D216,0),0) -> 0 | F216: =IF(E215>0,$H$5,0) -> 0 | G216: 0 | H216: =IF(B216>0,B216+F216,0) -> 0 | I216: =IF(E216>0,EDATE($B$8,A216-1),"") | J216: No
A217: TOTAL | B217: =SUMIF(B17:B216,">0") -> 12314.07 | C217: =SUMIF(C17:C216,">0") -> 2314.07 | D217: =SUMIF(D17:D216,">0") -> 10000 | F217: =SUMIF(F17:F216,">0") -> 540 | G217: =SUM(G17:G216) -> 0 | H217: =SUMIF(H17:H216,">0") -> 12854.07
A219: SUMMARY
A220: Original Principal: | B220: =$B$5 -> 10000
A221: Total Interest Paid: | B221: =C217 -> 2314.07
A222: Total Fees Paid: | B222: =F217 -> 540
A223: Total Amount Paid: | B223: =H217 -> 12854.07
A224: Total Months: | B224: =COUNTIF(B17:B216,">0") -> 36
A225: Cost Ratio (Total/Principal): | B225: =H217/$B$5 -> 1.285407
A226: Interest Savings from Extra: | B226: =$E$12 -> 36

Sheet Dashboard
A1: DEBT DASHBOARD - CONSOLIDATED VIEW
A2: All data updates automatically from individual credit sheets
A4: 1. LOAN SUMMARY
A5: Loan | B5: Principal | C5: Rate | D5: Payment | E5: Fees | F5: Total Monthly | G5: Months Left | H5: Payoff Date | I5: Total Interest | J5: Total Fees | K5: Loan | L5: Rate | M5: Principal | N5: Rank
A6: =Credit_1!B4 -> Car Loan | B6: =Credit_1!B5 -> 30000 | C6: =Credit_1!B6 -> 0.19 | D6: =Credit_1!E5 -> 531.35841 | E6: =Credit_1!H5 -> 25 | F6: =D6+E6 -> 556.35841 | G6: =Credit_1!B12 -> 3869.0752 | H6: =Credit_1!B11 -> 3 | I6: =Credit_1!C217 -> 25447.95 | J6: =Credit_1!F217 -> 2525 | K6: =Credit_1!B4 -> Car Loan | L6: =Credit_1!B6 -> 0.19 | M6: =Credit_1!B5 -> 30000 | N6: =RANK(L6,$L$6:$L$8,0) -> 1
A7: =Credit_2!B4 -> Home Mortgage | B7: =Credit_2!B5 -> 150000 | C7: =Credit_2!B6 -> 0.065 | D7: =Credit_2!E5 -> 1291.375 | E7: =Credit_2!H5 -> 150 | F7: =D7+E7 -> 1441.375 | G7: =Credit_2!B12 -> 0 | H7: =Credit_2!B11 -> 0 | I7: =Credit_2!C217 -> 82447.46 | J7: =Credit_2!F217 -> 27000 | K7: =Credit_2!B4 -> Home Mortgage | L7: =Credit_2!B6 -> 0.065 | M7: =Credit_2!B5 -> 150000 | N7: =RANK(L7,$L$6:$L$8,0) -> 3
A8: =Credit_3!B4 -> Personal Loan | B8: =Credit_3!B5 -> 10000 | C8: =Credit_3!B6 -> 0.15 | D8: =Credit_3!E5 -> 342.05758 | E8: =Credit_3!H5 -> 15 | F8: =D8+E8 -> 357.05758 | G8: =Credit_3!B12 -> 0 | H8: =Credit_3!B11 -> 0 | I8: =Credit_3!C217 -> 2314.07 | J8: =Credit_3!F217 -> 540 | K8: =Credit_3!B4 -> Personal Loan | L8: =Credit_3!B6 -> 0.15 | M8: =Credit_3!B5 -> 10000 | N8: =RANK(L8,$L$6:$L$8,0) -> 2
A9: TOTAL | B9: =SUM(B6:B8) -> 190000 | D9: =SUM(D6:D8) -> 2164.791 | E9: =SUM(E6:E8) -> 190 | F9: =SUM(F6:F8) -> 2354.791 | G9: =SUM(G6:G8) -> 3869.0752 | I9: =SUM(I6:I8) -> 110209.48 | J9: =SUM(J6:J8) -> 30065
A11: 2. CONSOLIDATED METRICS
A12: Total Debt: | B12: =B9 -> 190000 | D12: Total Interest to Pay: | E12: =I9 -> 110209.48
A13: Monthly Payment (excl. fees): | B13: =D9 -> 2164.791 | D13: Total Fees to Pay: | E13: =J9 -> 30065
A14: Monthly Fees: | B14: =E9 -> 190 | D14: Grand Total to Pay: | E14: =B9+I9+J9 -> 330274.48
A15: True Monthly Cost: | B15: =F9 -> 2354.791
A17: 3. PAYMENT PRIORITY (Highest Rate First = Avalanche Method)
A18: Priority | B18: Loan | C18: Interest Rate | D18: Balance | E18: Recommendation
A19: 1 | B19: =INDEX($K$6:$K$8,MATCH(1,$N$6:$N$8,0)) -> Car Loan | C19: =INDEX($L$6:$L$8,MATCH(1,$N$6:$N$8,0)) -> 0.19 | D19: =INDEX($M$6:$M$8,MATCH(1,$N$6:$N$8,0)) -> 30000 | E19: HIGH PRIORITY - Pay extra here first
A20: 2 | B20: =INDEX($K$6:$K$8,MATCH(2,$N$6:$N$8,0)) -> Personal Loan | C20: =INDEX($L$6:$L$8,MATCH(2,$N$6:$N$8,0)) -> 0.15 | D20: =INDEX($M$6:$M$8,MATCH(2,$N$6:$N$8,0)) -> 10000 | E20: MEDIUM PRIORITY
A21: 3 | B21: =INDEX($K$6:$K$8,MATCH(3,$N$6:$N$8,0)) -> Home Mortgage | C21: =INDEX($L$6:$L$8,MATCH(3,$N$6:$N$8,0)) -> 0.065 | D21: =INDEX($M$6:$M$8,MATCH(3,$N$6:$N$8,0)) -> 150000 | E21: LOWER PRIORITY - Lowest rate
A23: 4. PAYMENT PROGRESS
A24: Loan | B24: Payments Made | C24: Amount Paid | D24: Progress | E24: Remaining Balance
A25: =Credit_1!B4 -> Car Loan | B25: =Credit_1!B11 -> 3 | C25: =Credit_1!B12 -> 3869.0752 | D25: =Credit_1!B13 -> 0.02970297 | E25: =Credit_1!E13 -> 27498.345
A26: =Credit_2!B4 -> Home Mortgage | B26: =Credit_2!B11 -> 0 | C26: =Credit_2!B12 -> 0 | D26: =Credit_2!B13 -> 0 | E26: =Credit_2!E13 -> 150000
A27: =Credit_3!B4 -> Personal Loan | B27: =Credit_3!B11 -> 0 | C27: =Credit_3!B12 -> 0 | D27: =Credit_3!B13 -> 0 | E27: =Credit_3!E13 -> 10000
A28: TOTAL | B28: =SUM(B25:B27) -> 3 | C28: =SUM(C25:C27) -> 3869.0752 | D28: =IF(B28>0,B28/(Credit_1!E12+Credit_2!E12+Credit_3!E12),0) -> 0.0094637224 | E28: =SUM(E25:E27) -> 187498.34
A30: Created by Juan Perea Possos | linkedin.com/in/juanpereapossos | Free to use and share
